{"nodes": [{"id": "redis_service", "label": "redis-service.ts", "file_type": "code", "source_file": "apps\\server\\src\\services\\redis-service.ts", "source_location": "L1"}, {"id": "redis_service_connectredis", "label": "connectRedis()", "file_type": "code", "source_file": "apps\\server\\src\\services\\redis-service.ts", "source_location": "L14"}, {"id": "redis_service_ratelimiter", "label": "RateLimiter", "file_type": "code", "source_file": "apps\\server\\src\\services\\redis-service.ts", "source_location": "L21"}, {"id": "redis_service_ratelimiter_check", "label": ".check()", "file_type": "code", "source_file": "apps\\server\\src\\services\\redis-service.ts", "source_location": "L22"}], "edges": [{"source": "redis_service", "target": "redis", "relation": "imports_from", "confidence": "EXTRACTED", "source_file": "apps\\server\\src\\services\\redis-service.ts", "source_location": "L1", "weight": 1.0}, {"source": "redis_service", "target": "dotenv", "relation": "imports_from", "confidence": "EXTRACTED", "source_file": "apps\\server\\src\\services\\redis-service.ts", "source_location": "L2", "weight": 1.0}, {"source": "redis_service", "target": "redis_service_connectredis", "relation": "contains", "confidence": "EXTRACTED", "source_file": "apps\\server\\src\\services\\redis-service.ts", "source_location": "L14", "weight": 1.0}, {"source": "redis_service", "target": "redis_service_ratelimiter", "relation": "contains", "confidence": "EXTRACTED", "source_file": "apps\\server\\src\\services\\redis-service.ts", "source_location": "L21", "weight": 1.0}, {"source": "redis_service_ratelimiter", "target": "redis_service_ratelimiter_check", "relation": "method", "confidence": "EXTRACTED", "source_file": "apps\\server\\src\\services\\redis-service.ts", "source_location": "L22", "weight": 1.0}]}